pypi_token_client/__init__.py
pypi_token_client/app.py
pypi_token_client/async_client.py
pypi_token_client/cli.py
pypi_token_client/common.py
pypi_token_client/credentials.py
pypi_token_client/sync_client.py
pypi_token_client/utils/__init__.py
pypi_token_client/utils/playwright.py
pypi_token_client/utils/sequences.py
pypi_token_client-1.0.0.dist-info/entry_points.txt
pypi_token_client-1.0.0.dist-info/WHEEL
pypi_token_client-1.0.0.dist-info/METADATA
pypi_token_client-1.0.0.dist-info/RECORD
