Metadata-Version: 2.1
Name: pypi-token-client
Version: 1.0.0
Summary: Library and CLI tool for retrieving PyPI project tokens
Author: smheidrich
Author-email: smheidrich@weltenfunktion.de
Requires-Python: >=3.10,<4.0
Classifier: Programming Language :: Python :: 3
Classifier: Programming Language :: Python :: 3.10
Classifier: Programming Language :: Python :: 3.11
Requires-Dist: keyring (>=23.13.1,<24.0.0)
Requires-Dist: playwright (>=1.29,<2.0)
Requires-Dist: python-dateutil (>=2.8.2,<3.0.0)
Requires-Dist: typer (>=0.7.0,<0.8.0)
